MANIFEST.in
README.txt
setup.cfg
setup.py
Avery/__init__.py
Avery/__init__.pyc
Avery.egg-info/PKG-INFO
Avery.egg-info/SOURCES.txt
Avery.egg-info/dependency_links.txt
Avery.egg-info/requires.txt
Avery.egg-info/top_level.txt
Avery/interaction/__init__.py
Avery/interaction/widgets.py
static/widgets/js/widget_alert.js
static/widgets/js/widget_select.js