Metadata-Version: 1.1
Name: Avery
Version: 0.1.0
Summary: Miscellaneous packages
Home-page: https://pypi.python.org/pypi/Avery
Author: Leon Avery
Author-email: lavery3@vcu.edu
License: UNKNOWN
Platform: UNKNOWN
Classifier: Development Status :: 2 - Pre-Alpha
Classifier: Environment :: Web Environment
Classifier: Framework :: IPython
Classifier: Intended Audience :: Developers
Classifier: Intended Audience :: Science/Research
Classifier: License :: Free for non-commercial use
Classifier: Programming Language :: Python
Classifier: Programming Language :: JavaScript
Classifier: Topic :: Software Development :: Widget Sets
Requires: ipython
Requires: IPython.html
Requires: IPython.utils.traitlets
